{"ref":"refs/heads/master","after":"3744b272d36774a546e3b3031b0b7c9647870089","before":"b3e3d7e47a56f54e367ec711dd0af28029dfed8c","created":false,"deleted":false,"forced":false,"compare":"https://github.com/RReverser/douhack_sync/compare/b3e3d7e47a56...3744b272d367","commits":[{"id":"3744b272d36774a546e3b3031b0b7c9647870089","distinct":true,"message":"file1 edited online with Bitbucket","timestamp":"2013-05-18T23:46:27-07:00","url":"https://github.com/RReverser/douhack_sync/commit/3744b272d36774a546e3b3031b0b7c9647870089","author":{"name":"Ingvar Stepanyan","email":"me@rreverser.com","username":"RReverser"},"committer":{"name":"Ingvar Stepanyan","email":"me@rreverser.com","username":"RReverser"},"added":[],"removed":[],"modified":["file1"]}],"head_commit":{"id":"3744b272d36774a546e3b3031b0b7c9647870089","distinct":true,"message":"file1 edited online with Bitbucket","timestamp":"2013-05-18T23:46:27-07:00","url":"https://github.com/RReverser/douhack_sync/commit/3744b272d36774a546e3b3031b0b7c9647870089","author":{"name":"Ingvar Stepanyan","email":"me@rreverser.com","username":"RReverser"},"committer":{"name":"Ingvar Stepanyan","email":"me@rreverser.com","username":"RReverser"},"added":[],"removed":[],"modified":["file1"]},"repository":{"id":10149396,"name":"douhack_sync","url":"https://github.com/RReverser/douhack_sync","description":"","watchers":0,"stargazers":0,"forks":0,"fork":true,"size":180,"owner":{"name":"RReverser","email":"me@rreverser.com"},"private":false,"open_issues":0,"has_issues":false,"has_downloads":true,"has_wiki":true,"created_at":1368926585,"pushed_at":1368945995,"master_branch":"master"},"pusher":{"name":"RReverser","email":"me@rreverser.com"}}